relion/__init__.py
relion/bibtex.py
relion/constants.py
relion/objects.py
relion/protocols.conf
relion/relion_logo.jpg
relion/wizards.py
relion/convert/__init__.py
relion/convert/convert30.py
relion/convert/convert31.py
relion/convert/convert_base.py
relion/convert/convert_coordinates.py
relion/convert/convert_deprecated.py
relion/convert/convert_utils.py
relion/convert/dataimport.py
relion/convert/mtfs/mtf_apollo_300_ec_stdres.star
relion/convert/mtfs/mtf_apollo_300_ec_superres.star
relion/convert/mtfs/mtf_de20_300.star
relion/convert/mtfs/mtf_eigerX500K_100.star
relion/convert/mtfs/mtf_f1_300.star
relion/convert/mtfs/mtf_f2_300.star
relion/convert/mtfs/mtf_f3_200_ec.star
relion/convert/mtfs/mtf_f3_200_linear.star
relion/convert/mtfs/mtf_f3_300_ec.star
relion/convert/mtfs/mtf_f4_200_ec.star
relion/convert/mtfs/mtf_f4_300_ec.star
relion/convert/mtfs/mtf_k2_200_ec.star
relion/convert/mtfs/mtf_k2_300_ec.star
relion/protocols/__init__.py
relion/protocols/protocol_assign_optic_groups.py
relion/protocols/protocol_autopick.py
relion/protocols/protocol_autopick_log.py
relion/protocols/protocol_autopick_ref.py
relion/protocols/protocol_base.py
relion/protocols/protocol_bayesian_polishing.py
relion/protocols/protocol_calculate_fsc.py
relion/protocols/protocol_center_averages.py
relion/protocols/protocol_classify2d.py
relion/protocols/protocol_classify3d.py
relion/protocols/protocol_compress_movies_tasks.py
relion/protocols/protocol_copy_scratch.py
relion/protocols/protocol_create_mask3d.py
relion/protocols/protocol_crop_resize.py
relion/protocols/protocol_ctf_refinement.py
relion/protocols/protocol_dynamight.py
relion/protocols/protocol_estimate_gain.py
relion/protocols/protocol_expand_symmetry.py
relion/protocols/protocol_export_coords.py
relion/protocols/protocol_export_ctf.py
relion/protocols/protocol_export_particles.py
relion/protocols/protocol_extract_particles.py
relion/protocols/protocol_gentle_clean.py
relion/protocols/protocol_initialmodel.py
scipion_em_relion-5.0.2.dist-info/LICENSE
scipion_em_relion-5.0.2.dist-info/METADATA
scipion_em_relion-5.0.2.dist-info/WHEEL
scipion_em_relion-5.0.2.dist-info/entry_points.txt
scipion_em_relion-5.0.2.dist-info/top_level.txt
scipion_em_relion-5.0.2.dist-info/RECORD
