Metadata-Version: 2.1
Name: scipion-em-relion
Version: 5.0.2
Summary: Plugin to use Relion programs within the Scipion framework
Home-page: https://github.com/scipion-em/scipion-em-relion
Author: Grigory Sharov, J.M. De la Rosa Trevin, Josue Gomez Blanco
Author-email: gsharov@mrc-lmb.cam.ac.uk, delarosatrevin@scilifelab.se, josue.gomez-blanco@mcgill.ca
Project-URL: Bug Reports, https://github.com/scipion-em/scipion-em-relion/issues
Project-URL: Source, https://github.com/scipion-em/scipion-em-relion/
Keywords: scipion electron-microscopy cryo-em structural-biology image-processing scipion-3.0
Classifier: Development Status :: 5 - Production/Stable
Classifier: License :: OSI Approved :: GNU General Public License v3 (GPLv3)
Classifier: Programming Language :: Python :: 3
License-File: LICENSE
Requires-Dist: scipion-em
Requires-Dist: emtable>=0.0.14
Requires-Dist: emtools==0.1.0
